GPminer/__init__.py
GPminer/eval.py
GPminer/gen.py
GPminer/ind.py
GPminer/ino.py
GPminer/popu.py
GPminer/work.py
GPminer-2.2.0.dist-info/LICENSE
GPminer-2.2.0.dist-info/METADATA
GPminer-2.2.0.dist-info/WHEEL
GPminer-2.2.0.dist-info/top_level.txt
GPminer-2.2.0.dist-info/RECORD
