Metadata-Version: 2.1
Name: GPminer
Version: 2.2.0
Summary: Package for factor strategy mining by GP algorithm
Home-page: https://github.com/LHanLi/GPminer
Author: LH.Li
Author-email: lh98lee@zju.edu.cn
Classifier: Programming Language :: Python :: 3
Classifier: License :: OSI Approved :: GNU General Public License v3 or later (GPLv3+)
Classifier: Operating System :: OS Independent
License-File: LICENSE
